{
  "version": "7",
  "dialect": "postgresql",
  "entries": [
    {
      "idx": 0,
      "version": "7",
      "when": 1749808280315,
      "tag": "0000_cute_captain_midlands",
      "breakpoints": true
    },
    {
      "idx": 1,
      "version": "7",
      "when": 1750931283346,
      "tag": "0001_nice_thunderbolt",
      "breakpoints": true
    },
    {
      "idx": 2,
      "version": "7",
      "when": 1750953747761,
      "tag": "0002_curious_iceman",
      "breakpoints": true
    }
  ]
}